typedb_query_builder/__init__.py
typedb_query_builder/typedb_loader.py
typedb_query_builder/typedb_query_builder.py
typedb_query_builder/utils.py
typedb_query_builder-0.0.4.dist-info/LICENSE
typedb_query_builder-0.0.4.dist-info/METADATA
typedb_query_builder-0.0.4.dist-info/WHEEL
typedb_query_builder-0.0.4.dist-info/top_level.txt
typedb_query_builder-0.0.4.dist-info/RECORD
