Metadata-Version: 2.1
Name: typedb-query-builder
Version: 0.0.4
Summary: A lightweight package for building TypeDB queries.
Home-page: https://github.com/konradmy/typedb-query-builder
Author: Konrad Mysliwiec
Author-email: konradmy@gmail.com
License: UNKNOWN
Project-URL: Bug Tracker, https://github.com/konradmy/typedb-query-builder/issues
Platform: UNKNOWN
Classifier: Programming Language :: Python :: 3
Classifier: License :: OSI Approved :: MIT License
Classifier: Operating System :: OS Independent
Requires-Python: >=3.6
License-File: LICENSE
